NeuroBCL-0.1.2.dist-info/DESCRIPTION.rst
NeuroBCL-0.1.2.dist-info/METADATA
NeuroBCL-0.1.2.dist-info/RECORD
NeuroBCL-0.1.2.dist-info/WHEEL
NeuroBCL-0.1.2.dist-info/metadata.json
NeuroBCL-0.1.2.dist-info/top_level.txt
neurobcl/__init__.py
neurobcl/main.py
neurobcl/base/__init__.py
neurobcl/base/model.py
neurobcl/trainers/__init__.py
neurobcl/trainers/dictionary_trainer.py
