Metadata-Version: 2.0
Name: NeuroBCL
Version: 0.1.2
Summary: NeuroBCL (Neuro Bucket Classifier) is percentile based numeric feature normalizer that works to convert target bucket of numeric feature to its approximate bounds (Given multi-level features)
Author-email: Harishankar Kumar <hari01584@gmail.com>
License: MIT
Requires-Dist: sphinx>=7.2.6
Requires-Dist: furo>=2024.1.29
Requires-Dist: sphinx (>=7.2.6)
Requires-Dist: furo (>=2024.1.29)
